[{
  "_id": {
    "$oid": "65e7d3cccf9468ad1cf0050f"
  },
  "userId": {
    "$oid": "65cb95b7024d6854bb0b1592"
  },
  "postCommentId": {
    "$oid": "65e7d3c3cf9468ad1cf0041d"
  },
  "typeEvaluate": "post",
  "deleted": false,
  "createdAt": {
    "$date": "2024-03-06T02:24:12.243Z"
  },
  "updatedAt": {
    "$date": "2024-03-06T02:24:12.243Z"
  },
  "__v": 0
},
{
  "_id": {
    "$oid": "65e7d3cecf9468ad1cf00520"
  },
  "userId": {
    "$oid": "65cb95b7024d6854bb0b1592"
  },
  "postCommentId": {
    "$oid": "65daa148132a42ad74c121fb"
  },
  "typeEvaluate": "post",
  "deleted": false,
  "createdAt": {
    "$date": "2024-03-06T02:24:14.946Z"
  },
  "updatedAt": {
    "$date": "2024-03-06T02:24:14.946Z"
  },
  "__v": 0
}]